setup.py
algcxdb/__init__.py
algcxdb.egg-info/PKG-INFO
algcxdb.egg-info/SOURCES.txt
algcxdb.egg-info/dependency_links.txt
algcxdb.egg-info/top_level.txt